{
  "_format": "hh-sol-cache-2",
  "files": {
    "D:\\fruit-supply-chain\\contracts\\FruitSupplyChain.sol": {
      "lastModificationDate": 1743478958769,
      "contentHash": "34c9286ec4883e9246eda6c37f4f690a",
      "sourceName": "contracts/FruitSupplyChain.sol",
      "solcConfig": {
        "version": "0.8.28",
        "settings": {
          "evmVersion": "paris",
          "optimizer": {
            "enabled": false,
            "runs": 200
          },
          "outputSelection": {
            "*": {
              "*": [
                "abi",
                "evm.bytecode",
                "evm.deployedBytecode",
                "evm.methodIdentifiers",
                "metadata"
              ],
              "": [
                "ast"
              ]
            }
          }
        }
      },
      "imports": [],
      "versionPragmas": [
        "^0.8.28"
      ],
      "artifacts": [
        "FruitSupplyChain"
      ]
    }
  }
}
